{"matchStats": {"reports": {"onReport": []}, "sinBins": {"binned": []}, "created": "4:17:17pm", "matchInfo": {"period": 0, "matchType": "H", "finalCode": "", "homeSquadId": 332, "periodCompleted": 0, "finalShortCode": "", "venueName": "Accor Stadium", "matchStatus": "scheduled", "roundNumber": 16, "utcStartTime": "2026-06-20T09:30:00Z", "venueId": 9, "periodSeconds": 0, "awaySquadId": 336, "venueCode": "ASA", "localStartTime": "2026-06-20T19:30:00+10:00", "matchId": 129991604, "matchNumber": 4}, "playerInfo": {"player": [{"shortDisplayName": "Tracey, C", "firstname": "Connor", "surname": "Tracey", "displayName": "C.Tracey", "playerId": 997794}, {"shortDisplayName": "Kiraz, J", "firstname": "Jacob", "surname": "Kiraz", "displayName": "J.Kiraz", "playerId": 1025372}, {"shortDisplayName": "Xerri, B", "firstname": "Bronson", "surname": "Xerri", "displayName": "B.Xerri", "playerId": 1014514}, {"shortDisplayName": "Crichton, S", "firstname": "Stephen", "surname": "Crichton", "displayName": "S.Crichton", "playerId": 1018244}, {"shortDisplayName": "Tuala, E", "firstname": "Enari", "surname": "Tuala", "displayName": "E.Tuala", "playerId": 1008489}, {"shortDisplayName": "Burton, M", "firstname": "Matt", "surname": "Burton", "displayName": "M.Burton", "playerId": 1018383}, {"shortDisplayName": "Galvin, L", "firstname": "Lachlan", "surname": "Galvin", "displayName": "L.Galvin", "playerId": 1035354}, {"shortDisplayName": "King, M", "firstname": "Max", "surname": "King", "displayName": "M.King", "playerId": 1007459}, {"shortDisplayName": "Mann, K", "firstname": "Kurt", "surname": "Mann", "displayName": "K.Mann", "playerId": 31888}, {"shortDisplayName": "Thompson, L", "firstname": "Leo", "surname": "Thompson", "displayName": "L.Thompson", "playerId": 1025374}, {"shortDisplayName": "Tupouniua, S", "firstname": "Sitili", "surname": "Tupouniua", "displayName": "S.Tupouniua", "playerId": 1011034}, {"shortDisplayName": "Salmon, J", "firstname": "Jaeman", "surname": "Salmon", "displayName": "J.Salmon", "playerId": 1011017}, {"shortDisplayName": "Hayes, H", "firstname": "Harry", "surname": "Hayes", "displayName": "H.Hayes", "playerId": 1037474}, {"shortDisplayName": "Hayward, B", "firstname": "Bailey", "surname": "Hayward", "displayName": "B.Hayward", "playerId": 1035289}, {"shortDisplayName": "Reardon, J", "firstname": "Jed", "surname": "Reardon", "displayName": "J.Reardon", "playerId": 1048288}, {"shortDisplayName": "Underhill, J", "firstname": "Jack", "surname": "Underhill", "displayName": "J.Underhill", "playerId": 1038865}, {"shortDisplayName": "Curran, J", "firstname": "Josh", "surname": "Curran", "displayName": "J.Curran", "playerId": 1011036}, {"shortDisplayName": "Rinakama, J", "firstname": "Jethro", "surname": "Rinakama", "displayName": "J.Rinakama", "playerId": 1043598}, {"shortDisplayName": "Spinks, L", "firstname": "Logan", "surname": "Spinks", "displayName": "L.Spinks", "playerId": 1044788}, {"shortDisplayName": "Hopoi, L", "firstname": "Lipoi", "surname": "Hopoi", "displayName": "L.Hopoi", "playerId": 1037945}, {"shortDisplayName": "Conti, A", "firstname": "Alex", "surname": "Conti", "displayName": "A.Conti", "playerId": 1048080}, {"shortDisplayName": "Jones, A", "firstname": "Alekolasimi", "surname": "Jones", "displayName": "A.Jones", "playerId": 1045258}, {"shortDisplayName": "Trbojevic, T", "firstname": "Tom", "surname": "Trbojevic", "displayName": "T.Trbojevic", "playerId": 995915}, {"shortDisplayName": "Saab, J", "firstname": "Jason", "surname": "Saab", "displayName": "J.Saab", "playerId": 1014532}, {"shortDisplayName": "Koula, T", "firstname": "Tolutau", "surname": "Koula", "displayName": "T.Koula", "playerId": 1021750}, {"shortDisplayName": "Garrick, R", "firstname": "Reuben", "surname": "Garrick", "displayName": "R.Garrick", "playerId": 1002866}, {"shortDisplayName": "Hopoate, L", "firstname": "Lehi", "surname": "Hopoate", "displayName": "L.Hopoate", "playerId": 1035325}, {"shortDisplayName": "Brooks, L", "firstname": "Luke", "surname": "Brooks", "displayName": "L.Brooks", "playerId": 991722}, {"shortDisplayName": "Fogarty, J", "firstname": "Jamal", "surname": "Fogarty", "displayName": "J.Fogarty", "playerId": 991386}, {"shortDisplayName": "Paseka, T", "firstname": "Taniela", "surname": "Paseka", "displayName": "T.Paseka", "playerId": 1007404}, {"shortDisplayName": "Wakeham, B", "firstname": "Brandon", "surname": "Wakeham", "displayName": "B.Wakeham", "playerId": 1014513}, {"shortDisplayName": "Hetherington, K", "firstname": "Kobe", "surname": "Hetherington", "displayName": "K.Hetherington", "playerId": 1019538}, {"shortDisplayName": "Olakau'atu, H", "firstname": "Haumole", "surname": "Olakau'atu", "displayName": "H.Olakau'atu", "playerId": 1017275}, {"shortDisplayName": "Trbojevic, B", "firstname": "Ben", "surname": "Trbojevic", "displayName": "B.Trbojevic", "playerId": 1021284}, {"shortDisplayName": "Trbojevic, J", "firstname": "Jake", "surname": "Trbojevic", "displayName": "J.Trbojevic", "playerId": 991438}, {"shortDisplayName": "Simpkin, J", "firstname": "Jake", "surname": "Simpkin", "displayName": "J.Simpkin", "playerId": 1019596}, {"shortDisplayName": "Brown, N", "firstname": "Nathan", "surname": "Brown", "displayName": "N.Brown", "playerId": 1001235}, {"shortDisplayName": "Bullemor, E", "firstname": "Ethan", "surname": "Bullemor", "displayName": "E.Bullemor", "playerId": 1019536}, {"shortDisplayName": "Laiafi, S", "firstname": "Simione", "surname": "Laiafi", "displayName": "S.Laiafi", "playerId": 1043836}, {"shortDisplayName": "Feledy, J", "firstname": "Josh", "surname": "Feledy", "displayName": "J.Feledy", "playerId": 1034034}, {"shortDisplayName": "Walsh, J", "firstname": "Joey", "surname": "Walsh", "displayName": "J.Walsh", "playerId": 1039754}, {"shortDisplayName": "Hart, H", "firstname": "Hugo", "surname": "Hart", "displayName": "H.Hart", "playerId": 1048340}, {"shortDisplayName": "Wilson, B", "firstname": "Blake", "surname": "Wilson", "displayName": "B.Wilson", "playerId": 1033195}, {"shortDisplayName": "Shereb, J", "firstname": "Jackson", "surname": "Shereb", "displayName": "J.Shereb", "playerId": 1035329}]}, "periodInfo": {}, "teamInfo": {"team": [{"squadName": "Canterbury-Bankstown Bulldogs", "squadNickname": "Bulldogs", "squadCode": "CBB", "squadId": 332}, {"squadName": "Manly-Warringah Sea Eagles", "squadNickname": "Sea Eagles", "squadCode": "MWSE", "squadId": 336}]}, "jobId": 1781236126322, "playerStats": {"player": [{"tries": 0, "runsDummyHalfMetres": 0, "sinBins": 0, "onReports": 0, "runsHitupMetres": 0, "tryAssists": 0, "penaltyGoalAttempts": 0, "points": 0, "conversionsUnsuccessful": 0, "possessions": 0, "tackleds": 0, "kickMetres": 0, "kicksGeneralPlay": 0, "tackles": 0, "tacklesIneffective": 0, "handlingErrors": 0, "sentOffs": 0, "runsDummyHalf": 0, "squadId": 332, "offloads": 0, "bombKicksCaught": 0, "runsKickReturn": 0, "runsHitup": 0, "fieldGoalAttempts": 0, "conversionAttempts": 0, "penaltiesConceded": 0, "postContactMetres": 0, "position": "Fullback", "errors": 0, "goalLineDropouts": 0, "fortyTwenty": 0, "conversions": 0, "tryDebits": 0, "missedTackles": 0, "penaltyGoalsUnsuccessful": 0, "kicksCaught": 0, "metresGained": 0, "lineBreaks": 0, "tackleBreaks": 0, "trySaves": 0, "passes": 0, "runMetres": 0, "fieldGoalsUnsuccessful": 0, "lineBreakAssists": 0, "runsNormalMetres": 0, "runsNormal": 0, "runsKickReturnMetres": 0, "playerId": 997794, "jumperNumber": 1, "fieldGoals": 0, "penaltyGoals": 0, "runs": 0}, {"tries": 0, "runsDummyHalfMetres": 0, "sinBins": 0, "onReports": 0, "runsHitupMetres": 0, "tryAssists": 0, "penaltyGoalAttempts": 0, "points": 0, "conversionsUnsuccessful": 0, "possessions": 0, "tackleds": 0, "kickMetres": 0, "kicksGeneralPlay": 0, "tackles": 0, "tacklesIneffective": 0, "handlingErrors": 0, "sentOffs": 0, "runsDummyHalf": 0, "squadId": 332, "offloads": 0, "bombKicksCaught": 0, "runsKickReturn": 0, "runsHitup": 0, "fieldGoalAttempts": 0, "conversionAttempts": 0, "penaltiesConceded": 0, "postContactMetres": 0, "position": "Wing", "errors": 0, "goalLineDropouts": 0, "fortyTwenty": 0, "conversions": 0, "tryDebits": 0, "missedTackles": 0, "penaltyGoalsUnsuccessful": 0, "kicksCaught": 0, "metresGained": 0, "lineBreaks": 0, "tackleBreaks": 0, "trySaves": 0, "passes": 0, "runMetres": 0, "fieldGoalsUnsuccessful": 0, "lineBreakAssists": 0, "runsNormalMetres": 0, "runsNormal": 0, "runsKickReturnMetres": 0, "playerId": 1025372, "jumperNumber": 2, "fieldGoals": 0, "penaltyGoals": 0, "runs": 0}, {"tries": 0, "runsDummyHalfMetres": 0, "sinBins": 0, "onReports": 0, "runsHitupMetres": 0, "tryAssists": 0, "penaltyGoalAttempts": 0, "points": 0, "conversionsUnsuccessful": 0, "possessions": 0, "tackleds": 0, "kickMetres": 0, "kicksGeneralPlay": 0, "tackles": 0, "tacklesIneffective": 0, "handlingErrors": 0, "sentOffs": 0, "runsDummyHalf": 0, "squadId": 332, "offloads": 0, "bombKicksCaught": 0, "runsKickReturn": 0, "runsHitup": 0, "fieldGoalAttempts": 0, "conversionAttempts": 0, "penaltiesConceded": 0, "postContactMetres": 0, "position": "Centre", "errors": 0, "goalLineDropouts": 0, "fortyTwenty": 0, "conversions": 0, "tryDebits": 0, "missedTackles": 0, "penaltyGoalsUnsuccessful": 0, "kicksCaught": 0, "metresGained": 0, "lineBreaks": 0, "tackleBreaks": 0, "trySaves": 0, "passes": 0, "runMetres": 0, "fieldGoalsUnsuccessful": 0, "lineBreakAssists": 0, "runsNormalMetres": 0, "runsNormal": 0, "runsKickReturnMetres": 0, "playerId": 1014514, "jumperNumber": 3, "fieldGoals": 0, "penaltyGoals": 0, "runs": 0}, {"tries": 0, "runsDummyHalfMetres": 0, "sinBins": 0, "onReports": 0, "runsHitupMetres": 0, "tryAssists": 0, "penaltyGoalAttempts": 0, "points": 0, "conversionsUnsuccessful": 0, "possessions": 0, "tackleds": 0, "kickMetres": 0, "kicksGeneralPlay": 0, "tackles": 0, "tacklesIneffective": 0, "handlingErrors": 0, "sentOffs": 0, "runsDummyHalf": 0, "squadId": 332, "offloads": 0, "bombKicksCaught": 0, "runsKickReturn": 0, "runsHitup": 0, "fieldGoalAttempts": 0, "conversionAttempts": 0, "penaltiesConceded": 0, "postContactMetres": 0, "position": "Centre", "errors": 0, "goalLineDropouts": 0, "fortyTwenty": 0, "conversions": 0, "tryDebits": 0, "missedTackles": 0, "penaltyGoalsUnsuccessful": 0, "kicksCaught": 0, "metresGained": 0, "lineBreaks": 0, "tackleBreaks": 0, "trySaves": 0, "passes": 0, "runMetres": 0, "fieldGoalsUnsuccessful": 0, "lineBreakAssists": 0, "runsNormalMetres": 0, "runsNormal": 0, "runsKickReturnMetres": 0, "playerId": 1018244, "jumperNumber": 4, "fieldGoals": 0, "penaltyGoals": 0, "runs": 0}, {"tries": 0, "runsDummyHalfMetres": 0, "sinBins": 0, "onReports": 0, "runsHitupMetres": 0, "tryAssists": 0, "penaltyGoalAttempts": 0, "points": 0, "conversionsUnsuccessful": 0, "possessions": 0, "tackleds": 0, "kickMetres": 0, "kicksGeneralPlay": 0, "tackles": 0, "tacklesIneffective": 0, "handlingErrors": 0, "sentOffs": 0, "runsDummyHalf": 0, "squadId": 332, "offloads": 0, "bombKicksCaught": 0, "runsKickReturn": 0, "runsHitup": 0, "fieldGoalAttempts": 0, "conversionAttempts": 0, "penaltiesConceded": 0, "postContactMetres": 0, "position": "Wing", "errors": 0, "goalLineDropouts": 0, "fortyTwenty": 0, "conversions": 0, "tryDebits": 0, "missedTackles": 0, "penaltyGoalsUnsuccessful": 0, "kicksCaught": 0, "metresGained": 0, "lineBreaks": 0, "tackleBreaks": 0, "trySaves": 0, "passes": 0, "runMetres": 0, "fieldGoalsUnsuccessful": 0, "lineBreakAssists": 0, "runsNormalMetres": 0, "runsNormal": 0, "runsKickReturnMetres": 0, "playerId": 1008489, "jumperNumber": 5, "fieldGoals": 0, "penaltyGoals": 0, "runs": 0}, {"tries": 0, "runsDummyHalfMetres": 0, "sinBins": 0, "onReports": 0, "runsHitupMetres": 0, "tryAssists": 0, "penaltyGoalAttempts": 0, "points": 0, "conversionsUnsuccessful": 0, "possessions": 0, "tackleds": 0, "kickMetres": 0, "kicksGeneralPlay": 0, "tackles": 0, "tacklesIneffective": 0, "handlingErrors": 0, "sentOffs": 0, "runsDummyHalf": 0, "squadId": 332, "offloads": 0, "bombKicksCaught": 0, "runsKickReturn": 0, "runsHitup": 0, "fieldGoalAttempts": 0, "conversionAttempts": 0, "penaltiesConceded": 0, "postContactMetres": 0, "position": "Five-Eighth", "errors": 0, "goalLineDropouts": 0, "fortyTwenty": 0, "conversions": 0, "tryDebits": 0, "missedTackles": 0, "penaltyGoalsUnsuccessful": 0, "kicksCaught": 0, "metresGained": 0, "lineBreaks": 0, "tackleBreaks": 0, "trySaves": 0, "passes": 0, "runMetres": 0, "fieldGoalsUnsuccessful": 0, "lineBreakAssists": 0, "runsNormalMetres": 0, "runsNormal": 0, "runsKickReturnMetres": 0, "playerId": 1018383, "jumperNumber": 6, "fieldGoals": 0, "penaltyGoals": 0, "runs": 0}, {"tries": 0, "runsDummyHalfMetres": 0, "sinBins": 0, "onReports": 0, "runsHitupMetres": 0, "tryAssists": 0, "penaltyGoalAttempts": 0, "points": 0, "conversionsUnsuccessful": 0, "possessions": 0, "tackleds": 0, "kickMetres": 0, "kicksGeneralPlay": 0, "tackles": 0, "tacklesIneffective": 0, "handlingErrors": 0, "sentOffs": 0, "runsDummyHalf": 0, "squadId": 332, "offloads": 0, "bombKicksCaught": 0, "runsKickReturn": 0, "runsHitup": 0, "fieldGoalAttempts": 0, "conversionAttempts": 0, "penaltiesConceded": 0, "postContactMetres": 0, "position": "Halfback", "errors": 0, "goalLineDropouts": 0, "fortyTwenty": 0, "conversions": 0, "tryDebits": 0, "missedTackles": 0, "penaltyGoalsUnsuccessful": 0, "kicksCaught": 0, "metresGained": 0, "lineBreaks": 0, "tackleBreaks": 0, "trySaves": 0, "passes": 0, "runMetres": 0, "fieldGoalsUnsuccessful": 0, "lineBreakAssists": 0, "runsNormalMetres": 0, "runsNormal": 0, "runsKickReturnMetres": 0, "playerId": 1035354, "jumperNumber": 7, "fieldGoals": 0, "penaltyGoals": 0, "runs": 0}, {"tries": 0, "runsDummyHalfMetres": 0, "sinBins": 0, "onReports": 0, "runsHitupMetres": 0, "tryAssists": 0, "penaltyGoalAttempts": 0, "points": 0, "conversionsUnsuccessful": 0, "possessions": 0, "tackleds": 0, "kickMetres": 0, "kicksGeneralPlay": 0, "tackles": 0, "tacklesIneffective": 0, "handlingErrors": 0, "sentOffs": 0, "runsDummyHalf": 0, "squadId": 332, "offloads": 0, "bombKicksCaught": 0, "runsKickReturn": 0, "runsHitup": 0, "fieldGoalAttempts": 0, "conversionAttempts": 0, "penaltiesConceded": 0, "postContactMetres": 0, "position": "Prop", "errors": 0, "goalLineDropouts": 0, "fortyTwenty": 0, "conversions": 0, "tryDebits": 0, "missedTackles": 0, "penaltyGoalsUnsuccessful": 0, "kicksCaught": 0, "metresGained": 0, "lineBreaks": 0, "tackleBreaks": 0, "trySaves": 0, "passes": 0, "runMetres": 0, "fieldGoalsUnsuccessful": 0, "lineBreakAssists": 0, "runsNormalMetres": 0, "runsNormal": 0, "runsKickReturnMetres": 0, "playerId": 1007459, "jumperNumber": 8, "fieldGoals": 0, "penaltyGoals": 0, "runs": 0}, {"tries": 0, "runsDummyHalfMetres": 0, "sinBins": 0, "onReports": 0, "runsHitupMetres": 0, "tryAssists": 0, "penaltyGoalAttempts": 0, "points": 0, "conversionsUnsuccessful": 0, "possessions": 0, "tackleds": 0, "kickMetres": 0, "kicksGeneralPlay": 0, "tackles": 0, "tacklesIneffective": 0, "handlingErrors": 0, "sentOffs": 0, "runsDummyHalf": 0, "squadId": 332, "offloads": 0, "bombKicksCaught": 0, "runsKickReturn": 0, "runsHitup": 0, "fieldGoalAttempts": 0, "conversionAttempts": 0, "penaltiesConceded": 0, "postContactMetres": 0, "position": "Hooker", "errors": 0, "goalLineDropouts": 0, "fortyTwenty": 0, "conversions": 0, "tryDebits": 0, "missedTackles": 0, "penaltyGoalsUnsuccessful": 0, "kicksCaught": 0, "metresGained": 0, "lineBreaks": 0, "tackleBreaks": 0, "trySaves": 0, "passes": 0, "runMetres": 0, "fieldGoalsUnsuccessful": 0, "lineBreakAssists": 0, "runsNormalMetres": 0, "runsNormal": 0, "runsKickReturnMetres": 0, "playerId": 31888, "jumperNumber": 9, "fieldGoals": 0, "penaltyGoals": 0, "runs": 0}, {"tries": 0, "runsDummyHalfMetres": 0, "sinBins": 0, "onReports": 0, "runsHitupMetres": 0, "tryAssists": 0, "penaltyGoalAttempts": 0, "points": 0, "conversionsUnsuccessful": 0, "possessions": 0, "tackleds": 0, "kickMetres": 0, "kicksGeneralPlay": 0, "tackles": 0, "tacklesIneffective": 0, "handlingErrors": 0, "sentOffs": 0, "runsDummyHalf": 0, "squadId": 332, "offloads": 0, "bombKicksCaught": 0, "runsKickReturn": 0, "runsHitup": 0, "fieldGoalAttempts": 0, "conversionAttempts": 0, "penaltiesConceded": 0, "postContactMetres": 0, "position": "Prop", "errors": 0, "goalLineDropouts": 0, "fortyTwenty": 0, "conversions": 0, "tryDebits": 0, "missedTackles": 0, "penaltyGoalsUnsuccessful": 0, "kicksCaught": 0, "metresGained": 0, "lineBreaks": 0, "tackleBreaks": 0, "trySaves": 0, "passes": 0, "runMetres": 0, "fieldGoalsUnsuccessful": 0, "lineBreakAssists": 0, "runsNormalMetres": 0, "runsNormal": 0, "runsKickReturnMetres": 0, "playerId": 1025374, "jumperNumber": 10, "fieldGoals": 0, "penaltyGoals": 0, "runs": 0}, {"tries": 0, "runsDummyHalfMetres": 0, "sinBins": 0, "onReports": 0, "runsHitupMetres": 0, "tryAssists": 0, "penaltyGoalAttempts": 0, "points": 0, "conversionsUnsuccessful": 0, "possessions": 0, "tackleds": 0, "kickMetres": 0, "kicksGeneralPlay": 0, "tackles": 0, "tacklesIneffective": 0, "handlingErrors": 0, "sentOffs": 0, "runsDummyHalf": 0, "squadId": 332, "offloads": 0, "bombKicksCaught": 0, "runsKickReturn": 0, "runsHitup": 0, "fieldGoalAttempts": 0, "conversionAttempts": 0, "penaltiesConceded": 0, "postContactMetres": 0, "position": "Second Row", "errors": 0, "goalLineDropouts": 0, "fortyTwenty": 0, "conversions": 0, "tryDebits": 0, "missedTackles": 0, "penaltyGoalsUnsuccessful": 0, "kicksCaught": 0, "metresGained": 0, "lineBreaks": 0, "tackleBreaks": 0, "trySaves": 0, "passes": 0, "runMetres": 0, "fieldGoalsUnsuccessful": 0, "lineBreakAssists": 0, "runsNormalMetres": 0, "runsNormal": 0, "runsKickReturnMetres": 0, "playerId": 1011034, "jumperNumber": 11, "fieldGoals": 0, "penaltyGoals": 0, "runs": 0}, {"tries": 0, "runsDummyHalfMetres": 0, "sinBins": 0, "onReports": 0, "runsHitupMetres": 0, "tryAssists": 0, "penaltyGoalAttempts": 0, "points": 0, "conversionsUnsuccessful": 0, "possessions": 0, "tackleds": 0, "kickMetres": 0, "kicksGeneralPlay": 0, "tackles": 0, "tacklesIneffective": 0, "handlingErrors": 0, "sentOffs": 0, "runsDummyHalf": 0, "squadId": 332, "offloads": 0, "bombKicksCaught": 0, "runsKickReturn": 0, "runsHitup": 0, "fieldGoalAttempts": 0, "conversionAttempts": 0, "penaltiesConceded": 0, "postContactMetres": 0, "position": "Second Row", "errors": 0, "goalLineDropouts": 0, "fortyTwenty": 0, "conversions": 0, "tryDebits": 0, "missedTackles": 0, "penaltyGoalsUnsuccessful": 0, "kicksCaught": 0, "metresGained": 0, "lineBreaks": 0, "tackleBreaks": 0, "trySaves": 0, "passes": 0, "runMetres": 0, "fieldGoalsUnsuccessful": 0, "lineBreakAssists": 0, "runsNormalMetres": 0, "runsNormal": 0, "runsKickReturnMetres": 0, "playerId": 1011017, "jumperNumber": 12, "fieldGoals": 0, "penaltyGoals": 0, "runs": 0}, {"tries": 0, "runsDummyHalfMetres": 0, "sinBins": 0, "onReports": 0, "runsHitupMetres": 0, "tryAssists": 0, "penaltyGoalAttempts": 0, "points": 0, "conversionsUnsuccessful": 0, "possessions": 0, "tackleds": 0, "kickMetres": 0, "kicksGeneralPlay": 0, "tackles": 0, "tacklesIneffective": 0, "handlingErrors": 0, "sentOffs": 0, "runsDummyHalf": 0, "squadId": 332, "offloads": 0, "bombKicksCaught": 0, "runsKickReturn": 0, "runsHitup": 0, "fieldGoalAttempts": 0, "conversionAttempts": 0, "penaltiesConceded": 0, "postContactMetres": 0, "position": "Lock", "errors": 0, "goalLineDropouts": 0, "fortyTwenty": 0, "conversions": 0, "tryDebits": 0, "missedTackles": 0, "penaltyGoalsUnsuccessful": 0, "kicksCaught": 0, "metresGained": 0, "lineBreaks": 0, "tackleBreaks": 0, "trySaves": 0, "passes": 0, "runMetres": 0, "fieldGoalsUnsuccessful": 0, "lineBreakAssists": 0, "runsNormalMetres": 0, "runsNormal": 0, "runsKickReturnMetres": 0, "playerId": 1037474, "jumperNumber": 13, "fieldGoals": 0, "penaltyGoals": 0, "runs": 0}, {"tries": 0, "runsDummyHalfMetres": 0, "sinBins": 0, "onReports": 0, "runsHitupMetres": 0, "tryAssists": 0, "penaltyGoalAttempts": 0, "points": 0, "conversionsUnsuccessful": 0, "possessions": 0, "tackleds": 0, "kickMetres": 0, "kicksGeneralPlay": 0, "tackles": 0, "tacklesIneffective": 0, "handlingErrors": 0, "sentOffs": 0, "runsDummyHalf": 0, "squadId": 332, "offloads": 0, "bombKicksCaught": 0, "runsKickReturn": 0, "runsHitup": 0, "fieldGoalAttempts": 0, "conversionAttempts": 0, "penaltiesConceded": 0, "postContactMetres": 0, "position": "Interchange", "errors": 0, "goalLineDropouts": 0, "fortyTwenty": 0, "conversions": 0, "tryDebits": 0, "missedTackles": 0, "penaltyGoalsUnsuccessful": 0, "kicksCaught": 0, "metresGained": 0, "lineBreaks": 0, "tackleBreaks": 0, "trySaves": 0, "passes": 0, "runMetres": 0, "fieldGoalsUnsuccessful": 0, "lineBreakAssists": 0, "runsNormalMetres": 0, "runsNormal": 0, "runsKickReturnMetres": 0, "playerId": 1035289, "jumperNumber": 14, "fieldGoals": 0, "penaltyGoals": 0, "runs": 0}, {"tries": 0, "runsDummyHalfMetres": 0, "sinBins": 0, "onReports": 0, "runsHitupMetres": 0, "tryAssists": 0, "penaltyGoalAttempts": 0, "points": 0, "conversionsUnsuccessful": 0, "possessions": 0, "tackleds": 0, "kickMetres": 0, "kicksGeneralPlay": 0, "tackles": 0, "tacklesIneffective": 0, "handlingErrors": 0, "sentOffs": 0, "runsDummyHalf": 0, "squadId": 332, "offloads": 0, "bombKicksCaught": 0, "runsKickReturn": 0, "runsHitup": 0, "fieldGoalAttempts": 0, "conversionAttempts": 0, "penaltiesConceded": 0, "postContactMetres": 0, "position": "Interchange", "errors": 0, "goalLineDropouts": 0, "fortyTwenty": 0, "conversions": 0, "tryDebits": 0, "missedTackles": 0, "penaltyGoalsUnsuccessful": 0, "kicksCaught": 0, "metresGained": 0, "lineBreaks": 0, "tackleBreaks": 0, "trySaves": 0, "passes": 0, "runMetres": 0, "fieldGoalsUnsuccessful": 0, "lineBreakAssists": 0, "runsNormalMetres": 0, "runsNormal": 0, "runsKickReturnMetres": 0, "playerId": 1048288, "jumperNumber": 15, "fieldGoals": 0, "penaltyGoals": 0, "runs": 0}, {"tries": 0, "runsDummyHalfMetres": 0, "sinBins": 0, "onReports": 0, "runsHitupMetres": 0, "tryAssists": 0, "penaltyGoalAttempts": 0, "points": 0, "conversionsUnsuccessful": 0, "possessions": 0, "tackleds": 0, "kickMetres": 0, "kicksGeneralPlay": 0, "tackles": 0, "tacklesIneffective": 0, "handlingErrors": 0, "sentOffs": 0, "runsDummyHalf": 0, "squadId": 332, "offloads": 0, "bombKicksCaught": 0, "runsKickReturn": 0, "runsHitup": 0, "fieldGoalAttempts": 0, "conversionAttempts": 0, "penaltiesConceded": 0, "postContactMetres": 0, "position": "Interchange", "errors": 0, "goalLineDropouts": 0, "fortyTwenty": 0, "conversions": 0, "tryDebits": 0, "missedTackles": 0, "penaltyGoalsUnsuccessful": 0, "kicksCaught": 0, "metresGained": 0, "lineBreaks": 0, "tackleBreaks": 0, "trySaves": 0, "passes": 0, "runMetres": 0, "fieldGoalsUnsuccessful": 0, "lineBreakAssists": 0, "runsNormalMetres": 0, "runsNormal": 0, "runsKickReturnMetres": 0, "playerId": 1038865, "jumperNumber": 16, "fieldGoals": 0, "penaltyGoals": 0, "runs": 0}, {"tries": 0, "runsDummyHalfMetres": 0, "sinBins": 0, "onReports": 0, "runsHitupMetres": 0, "tryAssists": 0, "penaltyGoalAttempts": 0, "points": 0, "conversionsUnsuccessful": 0, "possessions": 0, "tackleds": 0, "kickMetres": 0, "kicksGeneralPlay": 0, "tackles": 0, "tacklesIneffective": 0, "handlingErrors": 0, "sentOffs": 0, "runsDummyHalf": 0, "squadId": 332, "offloads": 0, "bombKicksCaught": 0, "runsKickReturn": 0, "runsHitup": 0, "fieldGoalAttempts": 0, "conversionAttempts": 0, "penaltiesConceded": 0, "postContactMetres": 0, "position": "Interchange", "errors": 0, "goalLineDropouts": 0, "fortyTwenty": 0, "conversions": 0, "tryDebits": 0, "missedTackles": 0, "penaltyGoalsUnsuccessful": 0, "kicksCaught": 0, "metresGained": 0, "lineBreaks": 0, "tackleBreaks": 0, "trySaves": 0, "passes": 0, "runMetres": 0, "fieldGoalsUnsuccessful": 0, "lineBreakAssists": 0, "runsNormalMetres": 0, "runsNormal": 0, "runsKickReturnMetres": 0, "playerId": 1011036, "jumperNumber": 17, "fieldGoals": 0, "penaltyGoals": 0, "runs": 0}, {"tries": 0, "runsDummyHalfMetres": 0, "sinBins": 0, "onReports": 0, "runsHitupMetres": 0, "tryAssists": 0, "penaltyGoalAttempts": 0, "points": 0, "conversionsUnsuccessful": 0, "possessions": 0, "tackleds": 0, "kickMetres": 0, "kicksGeneralPlay": 0, "tackles": 0, "tacklesIneffective": 0, "handlingErrors": 0, "sentOffs": 0, "runsDummyHalf": 0, "squadId": 332, "offloads": 0, "bombKicksCaught": 0, "runsKickReturn": 0, "runsHitup": 0, "fieldGoalAttempts": 0, "conversionAttempts": 0, "penaltiesConceded": 0, "postContactMetres": 0, "position": "Interchange", "errors": 0, "goalLineDropouts": 0, "fortyTwenty": 0, "conversions": 0, "tryDebits": 0, "missedTackles": 0, "penaltyGoalsUnsuccessful": 0, "kicksCaught": 0, "metresGained": 0, "lineBreaks": 0, "tackleBreaks": 0, "trySaves": 0, "passes": 0, "runMetres": 0, "fieldGoalsUnsuccessful": 0, "lineBreakAssists": 0, "runsNormalMetres": 0, "runsNormal": 0, "runsKickReturnMetres": 0, "playerId": 1043598, "jumperNumber": 19, "fieldGoals": 0, "penaltyGoals": 0, "runs": 0}, {"tries": 0, "runsDummyHalfMetres": 0, "sinBins": 0, "onReports": 0, "runsHitupMetres": 0, "tryAssists": 0, "penaltyGoalAttempts": 0, "points": 0, "conversionsUnsuccessful": 0, "possessions": 0, "tackleds": 0, "kickMetres": 0, "kicksGeneralPlay": 0, "tackles": 0, "tacklesIneffective": 0, "handlingErrors": 0, "sentOffs": 0, "runsDummyHalf": 0, "squadId": 332, "offloads": 0, "bombKicksCaught": 0, "runsKickReturn": 0, "runsHitup": 0, "fieldGoalAttempts": 0, "conversionAttempts": 0, "penaltiesConceded": 0, "postContactMetres": 0, "position": "Interchange", "errors": 0, "goalLineDropouts": 0, "fortyTwenty": 0, "conversions": 0, "tryDebits": 0, "missedTackles": 0, "penaltyGoalsUnsuccessful": 0, "kicksCaught": 0, "metresGained": 0, "lineBreaks": 0, "tackleBreaks": 0, "trySaves": 0, "passes": 0, "runMetres": 0, "fieldGoalsUnsuccessful": 0, "lineBreakAssists": 0, "runsNormalMetres": 0, "runsNormal": 0, "runsKickReturnMetres": 0, "playerId": 1044788, "jumperNumber": 20, "fieldGoals": 0, "penaltyGoals": 0, "runs": 0}, {"tries": 0, "runsDummyHalfMetres": 0, "sinBins": 0, "onReports": 0, "runsHitupMetres": 0, "tryAssists": 0, "penaltyGoalAttempts": 0, "points": 0, "conversionsUnsuccessful": 0, "possessions": 0, "tackleds": 0, "kickMetres": 0, "kicksGeneralPlay": 0, "tackles": 0, "tacklesIneffective": 0, "handlingErrors": 0, "sentOffs": 0, "runsDummyHalf": 0, "squadId": 332, "offloads": 0, "bombKicksCaught": 0, "runsKickReturn": 0, "runsHitup": 0, "fieldGoalAttempts": 0, "conversionAttempts": 0, "penaltiesConceded": 0, "postContactMetres": 0, "position": "Interchange", "errors": 0, "goalLineDropouts": 0, "fortyTwenty": 0, "conversions": 0, "tryDebits": 0, "missedTackles": 0, "penaltyGoalsUnsuccessful": 0, "kicksCaught": 0, "metresGained": 0, "lineBreaks": 0, "tackleBreaks": 0, "trySaves": 0, "passes": 0, "runMetres": 0, "fieldGoalsUnsuccessful": 0, "lineBreakAssists": 0, "runsNormalMetres": 0, "runsNormal": 0, "runsKickReturnMetres": 0, "playerId": 1037945, "jumperNumber": 21, "fieldGoals": 0, "penaltyGoals": 0, "runs": 0}, {"tries": 0, "runsDummyHalfMetres": 0, "sinBins": 0, "onReports": 0, "runsHitupMetres": 0, "tryAssists": 0, "penaltyGoalAttempts": 0, "points": 0, "conversionsUnsuccessful": 0, "possessions": 0, "tackleds": 0, "kickMetres": 0, "kicksGeneralPlay": 0, "tackles": 0, "tacklesIneffective": 0, "handlingErrors": 0, "sentOffs": 0, "runsDummyHalf": 0, "squadId": 332, "offloads": 0, "bombKicksCaught": 0, "runsKickReturn": 0, "runsHitup": 0, "fieldGoalAttempts": 0, "conversionAttempts": 0, "penaltiesConceded": 0, "postContactMetres": 0, "position": "Interchange", "errors": 0, "goalLineDropouts": 0, "fortyTwenty": 0, "conversions": 0, "tryDebits": 0, "missedTackles": 0, "penaltyGoalsUnsuccessful": 0, "kicksCaught": 0, "metresGained": 0, "lineBreaks": 0, "tackleBreaks": 0, "trySaves": 0, "passes": 0, "runMetres": 0, "fieldGoalsUnsuccessful": 0, "lineBreakAssists": 0, "runsNormalMetres": 0, "runsNormal": 0, "runsKickReturnMetres": 0, "playerId": 1048080, "jumperNumber": 21, "fieldGoals": 0, "penaltyGoals": 0, "runs": 0}, {"tries": 0, "runsDummyHalfMetres": 0, "sinBins": 0, "onReports": 0, "runsHitupMetres": 0, "tryAssists": 0, "penaltyGoalAttempts": 0, "points": 0, "conversionsUnsuccessful": 0, "possessions": 0, "tackleds": 0, "kickMetres": 0, "kicksGeneralPlay": 0, "tackles": 0, "tacklesIneffective": 0, "handlingErrors": 0, "sentOffs": 0, "runsDummyHalf": 0, "squadId": 332, "offloads": 0, "bombKicksCaught": 0, "runsKickReturn": 0, "runsHitup": 0, "fieldGoalAttempts": 0, "conversionAttempts": 0, "penaltiesConceded": 0, "postContactMetres": 0, "position": "Extended Bench 5", "errors": 0, "goalLineDropouts": 0, "fortyTwenty": 0, "conversions": 0, "tryDebits": 0, "missedTackles": 0, "penaltyGoalsUnsuccessful": 0, "kicksCaught": 0, "metresGained": 0, "lineBreaks": 0, "tackleBreaks": 0, "trySaves": 0, "passes": 0, "runMetres": 0, "fieldGoalsUnsuccessful": 0, "lineBreakAssists": 0, "runsNormalMetres": 0, "runsNormal": 0, "runsKickReturnMetres": 0, "playerId": 1045258, "jumperNumber": 23, "fieldGoals": 0, "penaltyGoals": 0, "runs": 0}, {"tries": 0, "runsDummyHalfMetres": 0, "sinBins": 0, "onReports": 0, "runsHitupMetres": 0, "tryAssists": 0, "penaltyGoalAttempts": 0, "points": 0, "conversionsUnsuccessful": 0, "possessions": 0, "tackleds": 0, "kickMetres": 0, "kicksGeneralPlay": 0, "tackles": 0, "tacklesIneffective": 0, "handlingErrors": 0, "sentOffs": 0, "runsDummyHalf": 0, "squadId": 336, "offloads": 0, "bombKicksCaught": 0, "runsKickReturn": 0, "runsHitup": 0, "fieldGoalAttempts": 0, "conversionAttempts": 0, "penaltiesConceded": 0, "postContactMetres": 0, "position": "Fullback", "errors": 0, "goalLineDropouts": 0, "fortyTwenty": 0, "conversions": 0, "tryDebits": 0, "missedTackles": 0, "penaltyGoalsUnsuccessful": 0, "kicksCaught": 0, "metresGained": 0, "lineBreaks": 0, "tackleBreaks": 0, "trySaves": 0, "passes": 0, "runMetres": 0, "fieldGoalsUnsuccessful": 0, "lineBreakAssists": 0, "runsNormalMetres": 0, "runsNormal": 0, "runsKickReturnMetres": 0, "playerId": 995915, "jumperNumber": 1, "fieldGoals": 0, "penaltyGoals": 0, "runs": 0}, {"tries": 0, "runsDummyHalfMetres": 0, "sinBins": 0, "onReports": 0, "runsHitupMetres": 0, "tryAssists": 0, "penaltyGoalAttempts": 0, "points": 0, "conversionsUnsuccessful": 0, "possessions": 0, "tackleds": 0, "kickMetres": 0, "kicksGeneralPlay": 0, "tackles": 0, "tacklesIneffective": 0, "handlingErrors": 0, "sentOffs": 0, "runsDummyHalf": 0, "squadId": 336, "offloads": 0, "bombKicksCaught": 0, "runsKickReturn": 0, "runsHitup": 0, "fieldGoalAttempts": 0, "conversionAttempts": 0, "penaltiesConceded": 0, "postContactMetres": 0, "position": "Wing", "errors": 0, "goalLineDropouts": 0, "fortyTwenty": 0, "conversions": 0, "tryDebits": 0, "missedTackles": 0, "penaltyGoalsUnsuccessful": 0, "kicksCaught": 0, "metresGained": 0, "lineBreaks": 0, "tackleBreaks": 0, "trySaves": 0, "passes": 0, "runMetres": 0, "fieldGoalsUnsuccessful": 0, "lineBreakAssists": 0, "runsNormalMetres": 0, "runsNormal": 0, "runsKickReturnMetres": 0, "playerId": 1014532, "jumperNumber": 2, "fieldGoals": 0, "penaltyGoals": 0, "runs": 0}, {"tries": 0, "runsDummyHalfMetres": 0, "sinBins": 0, "onReports": 0, "runsHitupMetres": 0, "tryAssists": 0, "penaltyGoalAttempts": 0, "points": 0, "conversionsUnsuccessful": 0, "possessions": 0, "tackleds": 0, "kickMetres": 0, "kicksGeneralPlay": 0, "tackles": 0, "tacklesIneffective": 0, "handlingErrors": 0, "sentOffs": 0, "runsDummyHalf": 0, "squadId": 336, "offloads": 0, "bombKicksCaught": 0, "runsKickReturn": 0, "runsHitup": 0, "fieldGoalAttempts": 0, "conversionAttempts": 0, "penaltiesConceded": 0, "postContactMetres": 0, "position": "Centre", "errors": 0, "goalLineDropouts": 0, "fortyTwenty": 0, "conversions": 0, "tryDebits": 0, "missedTackles": 0, "penaltyGoalsUnsuccessful": 0, "kicksCaught": 0, "metresGained": 0, "lineBreaks": 0, "tackleBreaks": 0, "trySaves": 0, "passes": 0, "runMetres": 0, "fieldGoalsUnsuccessful": 0, "lineBreakAssists": 0, "runsNormalMetres": 0, "runsNormal": 0, "runsKickReturnMetres": 0, "playerId": 1021750, "jumperNumber": 3, "fieldGoals": 0, "penaltyGoals": 0, "runs": 0}, {"tries": 0, "runsDummyHalfMetres": 0, "sinBins": 0, "onReports": 0, "runsHitupMetres": 0, "tryAssists": 0, "penaltyGoalAttempts": 0, "points": 0, "conversionsUnsuccessful": 0, "possessions": 0, "tackleds": 0, "kickMetres": 0, "kicksGeneralPlay": 0, "tackles": 0, "tacklesIneffective": 0, "handlingErrors": 0, "sentOffs": 0, "runsDummyHalf": 0, "squadId": 336, "offloads": 0, "bombKicksCaught": 0, "runsKickReturn": 0, "runsHitup": 0, "fieldGoalAttempts": 0, "conversionAttempts": 0, "penaltiesConceded": 0, "postContactMetres": 0, "position": "Centre", "errors": 0, "goalLineDropouts": 0, "fortyTwenty": 0, "conversions": 0, "tryDebits": 0, "missedTackles": 0, "penaltyGoalsUnsuccessful": 0, "kicksCaught": 0, "metresGained": 0, "lineBreaks": 0, "tackleBreaks": 0, "trySaves": 0, "passes": 0, "runMetres": 0, "fieldGoalsUnsuccessful": 0, "lineBreakAssists": 0, "runsNormalMetres": 0, "runsNormal": 0, "runsKickReturnMetres": 0, "playerId": 1002866, "jumperNumber": 4, "fieldGoals": 0, "penaltyGoals": 0, "runs": 0}, {"tries": 0, "runsDummyHalfMetres": 0, "sinBins": 0, "onReports": 0, "runsHitupMetres": 0, "tryAssists": 0, "penaltyGoalAttempts": 0, "points": 0, "conversionsUnsuccessful": 0, "possessions": 0, "tackleds": 0, "kickMetres": 0, "kicksGeneralPlay": 0, "tackles": 0, "tacklesIneffective": 0, "handlingErrors": 0, "sentOffs": 0, "runsDummyHalf": 0, "squadId": 336, "offloads": 0, "bombKicksCaught": 0, "runsKickReturn": 0, "runsHitup": 0, "fieldGoalAttempts": 0, "conversionAttempts": 0, "penaltiesConceded": 0, "postContactMetres": 0, "position": "Wing", "errors": 0, "goalLineDropouts": 0, "fortyTwenty": 0, "conversions": 0, "tryDebits": 0, "missedTackles": 0, "penaltyGoalsUnsuccessful": 0, "kicksCaught": 0, "metresGained": 0, "lineBreaks": 0, "tackleBreaks": 0, "trySaves": 0, "passes": 0, "runMetres": 0, "fieldGoalsUnsuccessful": 0, "lineBreakAssists": 0, "runsNormalMetres": 0, "runsNormal": 0, "runsKickReturnMetres": 0, "playerId": 1035325, "jumperNumber": 5, "fieldGoals": 0, "penaltyGoals": 0, "runs": 0}, {"tries": 0, "runsDummyHalfMetres": 0, "sinBins": 0, "onReports": 0, "runsHitupMetres": 0, "tryAssists": 0, "penaltyGoalAttempts": 0, "points": 0, "conversionsUnsuccessful": 0, "possessions": 0, "tackleds": 0, "kickMetres": 0, "kicksGeneralPlay": 0, "tackles": 0, "tacklesIneffective": 0, "handlingErrors": 0, "sentOffs": 0, "runsDummyHalf": 0, "squadId": 336, "offloads": 0, "bombKicksCaught": 0, "runsKickReturn": 0, "runsHitup": 0, "fieldGoalAttempts": 0, "conversionAttempts": 0, "penaltiesConceded": 0, "postContactMetres": 0, "position": "Five-Eighth", "errors": 0, "goalLineDropouts": 0, "fortyTwenty": 0, "conversions": 0, "tryDebits": 0, "missedTackles": 0, "penaltyGoalsUnsuccessful": 0, "kicksCaught": 0, "metresGained": 0, "lineBreaks": 0, "tackleBreaks": 0, "trySaves": 0, "passes": 0, "runMetres": 0, "fieldGoalsUnsuccessful": 0, "lineBreakAssists": 0, "runsNormalMetres": 0, "runsNormal": 0, "runsKickReturnMetres": 0, "playerId": 991722, "jumperNumber": 6, "fieldGoals": 0, "penaltyGoals": 0, "runs": 0}, {"tries": 0, "runsDummyHalfMetres": 0, "sinBins": 0, "onReports": 0, "runsHitupMetres": 0, "tryAssists": 0, "penaltyGoalAttempts": 0, "points": 0, "conversionsUnsuccessful": 0, "possessions": 0, "tackleds": 0, "kickMetres": 0, "kicksGeneralPlay": 0, "tackles": 0, "tacklesIneffective": 0, "handlingErrors": 0, "sentOffs": 0, "runsDummyHalf": 0, "squadId": 336, "offloads": 0, "bombKicksCaught": 0, "runsKickReturn": 0, "runsHitup": 0, "fieldGoalAttempts": 0, "conversionAttempts": 0, "penaltiesConceded": 0, "postContactMetres": 0, "position": "Halfback", "errors": 0, "goalLineDropouts": 0, "fortyTwenty": 0, "conversions": 0, "tryDebits": 0, "missedTackles": 0, "penaltyGoalsUnsuccessful": 0, "kicksCaught": 0, "metresGained": 0, "lineBreaks": 0, "tackleBreaks": 0, "trySaves": 0, "passes": 0, "runMetres": 0, "fieldGoalsUnsuccessful": 0, "lineBreakAssists": 0, "runsNormalMetres": 0, "runsNormal": 0, "runsKickReturnMetres": 0, "playerId": 991386, "jumperNumber": 7, "fieldGoals": 0, "penaltyGoals": 0, "runs": 0}, {"tries": 0, "runsDummyHalfMetres": 0, "sinBins": 0, "onReports": 0, "runsHitupMetres": 0, "tryAssists": 0, "penaltyGoalAttempts": 0, "points": 0, "conversionsUnsuccessful": 0, "possessions": 0, "tackleds": 0, "kickMetres": 0, "kicksGeneralPlay": 0, "tackles": 0, "tacklesIneffective": 0, "handlingErrors": 0, "sentOffs": 0, "runsDummyHalf": 0, "squadId": 336, "offloads": 0, "bombKicksCaught": 0, "runsKickReturn": 0, "runsHitup": 0, "fieldGoalAttempts": 0, "conversionAttempts": 0, "penaltiesConceded": 0, "postContactMetres": 0, "position": "Prop", "errors": 0, "goalLineDropouts": 0, "fortyTwenty": 0, "conversions": 0, "tryDebits": 0, "missedTackles": 0, "penaltyGoalsUnsuccessful": 0, "kicksCaught": 0, "metresGained": 0, "lineBreaks": 0, "tackleBreaks": 0, "trySaves": 0, "passes": 0, "runMetres": 0, "fieldGoalsUnsuccessful": 0, "lineBreakAssists": 0, "runsNormalMetres": 0, "runsNormal": 0, "runsKickReturnMetres": 0, "playerId": 1007404, "jumperNumber": 8, "fieldGoals": 0, "penaltyGoals": 0, "runs": 0}, {"tries": 0, "runsDummyHalfMetres": 0, "sinBins": 0, "onReports": 0, "runsHitupMetres": 0, "tryAssists": 0, "penaltyGoalAttempts": 0, "points": 0, "conversionsUnsuccessful": 0, "possessions": 0, "tackleds": 0, "kickMetres": 0, "kicksGeneralPlay": 0, "tackles": 0, "tacklesIneffective": 0, "handlingErrors": 0, "sentOffs": 0, "runsDummyHalf": 0, "squadId": 336, "offloads": 0, "bombKicksCaught": 0, "runsKickReturn": 0, "runsHitup": 0, "fieldGoalAttempts": 0, "conversionAttempts": 0, "penaltiesConceded": 0, "postContactMetres": 0, "position": "Hooker", "errors": 0, "goalLineDropouts": 0, "fortyTwenty": 0, "conversions": 0, "tryDebits": 0, "missedTackles": 0, "penaltyGoalsUnsuccessful": 0, "kicksCaught": 0, "metresGained": 0, "lineBreaks": 0, "tackleBreaks": 0, "trySaves": 0, "passes": 0, "runMetres": 0, "fieldGoalsUnsuccessful": 0, "lineBreakAssists": 0, "runsNormalMetres": 0, "runsNormal": 0, "runsKickReturnMetres": 0, "playerId": 1014513, "jumperNumber": 9, "fieldGoals": 0, "penaltyGoals": 0, "runs": 0}, {"tries": 0, "runsDummyHalfMetres": 0, "sinBins": 0, "onReports": 0, "runsHitupMetres": 0, "tryAssists": 0, "penaltyGoalAttempts": 0, "points": 0, "conversionsUnsuccessful": 0, "possessions": 0, "tackleds": 0, "kickMetres": 0, "kicksGeneralPlay": 0, "tackles": 0, "tacklesIneffective": 0, "handlingErrors": 0, "sentOffs": 0, "runsDummyHalf": 0, "squadId": 336, "offloads": 0, "bombKicksCaught": 0, "runsKickReturn": 0, "runsHitup": 0, "fieldGoalAttempts": 0, "conversionAttempts": 0, "penaltiesConceded": 0, "postContactMetres": 0, "position": "Prop", "errors": 0, "goalLineDropouts": 0, "fortyTwenty": 0, "conversions": 0, "tryDebits": 0, "missedTackles": 0, "penaltyGoalsUnsuccessful": 0, "kicksCaught": 0, "metresGained": 0, "lineBreaks": 0, "tackleBreaks": 0, "trySaves": 0, "passes": 0, "runMetres": 0, "fieldGoalsUnsuccessful": 0, "lineBreakAssists": 0, "runsNormalMetres": 0, "runsNormal": 0, "runsKickReturnMetres": 0, "playerId": 1019538, "jumperNumber": 10, "fieldGoals": 0, "penaltyGoals": 0, "runs": 0}, {"tries": 0, "runsDummyHalfMetres": 0, "sinBins": 0, "onReports": 0, "runsHitupMetres": 0, "tryAssists": 0, "penaltyGoalAttempts": 0, "points": 0, "conversionsUnsuccessful": 0, "possessions": 0, "tackleds": 0, "kickMetres": 0, "kicksGeneralPlay": 0, "tackles": 0, "tacklesIneffective": 0, "handlingErrors": 0, "sentOffs": 0, "runsDummyHalf": 0, "squadId": 336, "offloads": 0, "bombKicksCaught": 0, "runsKickReturn": 0, "runsHitup": 0, "fieldGoalAttempts": 0, "conversionAttempts": 0, "penaltiesConceded": 0, "postContactMetres": 0, "position": "Second Row", "errors": 0, "goalLineDropouts": 0, "fortyTwenty": 0, "conversions": 0, "tryDebits": 0, "missedTackles": 0, "penaltyGoalsUnsuccessful": 0, "kicksCaught": 0, "metresGained": 0, "lineBreaks": 0, "tackleBreaks": 0, "trySaves": 0, "passes": 0, "runMetres": 0, "fieldGoalsUnsuccessful": 0, "lineBreakAssists": 0, "runsNormalMetres": 0, "runsNormal": 0, "runsKickReturnMetres": 0, "playerId": 1017275, "jumperNumber": 11, "fieldGoals": 0, "penaltyGoals": 0, "runs": 0}, {"tries": 0, "runsDummyHalfMetres": 0, "sinBins": 0, "onReports": 0, "runsHitupMetres": 0, "tryAssists": 0, "penaltyGoalAttempts": 0, "points": 0, "conversionsUnsuccessful": 0, "possessions": 0, "tackleds": 0, "kickMetres": 0, "kicksGeneralPlay": 0, "tackles": 0, "tacklesIneffective": 0, "handlingErrors": 0, "sentOffs": 0, "runsDummyHalf": 0, "squadId": 336, "offloads": 0, "bombKicksCaught": 0, "runsKickReturn": 0, "runsHitup": 0, "fieldGoalAttempts": 0, "conversionAttempts": 0, "penaltiesConceded": 0, "postContactMetres": 0, "position": "Second Row", "errors": 0, "goalLineDropouts": 0, "fortyTwenty": 0, "conversions": 0, "tryDebits": 0, "missedTackles": 0, "penaltyGoalsUnsuccessful": 0, "kicksCaught": 0, "metresGained": 0, "lineBreaks": 0, "tackleBreaks": 0, "trySaves": 0, "passes": 0, "runMetres": 0, "fieldGoalsUnsuccessful": 0, "lineBreakAssists": 0, "runsNormalMetres": 0, "runsNormal": 0, "runsKickReturnMetres": 0, "playerId": 1021284, "jumperNumber": 12, "fieldGoals": 0, "penaltyGoals": 0, "runs": 0}, {"tries": 0, "runsDummyHalfMetres": 0, "sinBins": 0, "onReports": 0, "runsHitupMetres": 0, "tryAssists": 0, "penaltyGoalAttempts": 0, "points": 0, "conversionsUnsuccessful": 0, "possessions": 0, "tackleds": 0, "kickMetres": 0, "kicksGeneralPlay": 0, "tackles": 0, "tacklesIneffective": 0, "handlingErrors": 0, "sentOffs": 0, "runsDummyHalf": 0, "squadId": 336, "offloads": 0, "bombKicksCaught": 0, "runsKickReturn": 0, "runsHitup": 0, "fieldGoalAttempts": 0, "conversionAttempts": 0, "penaltiesConceded": 0, "postContactMetres": 0, "position": "Lock", "errors": 0, "goalLineDropouts": 0, "fortyTwenty": 0, "conversions": 0, "tryDebits": 0, "missedTackles": 0, "penaltyGoalsUnsuccessful": 0, "kicksCaught": 0, "metresGained": 0, "lineBreaks": 0, "tackleBreaks": 0, "trySaves": 0, "passes": 0, "runMetres": 0, "fieldGoalsUnsuccessful": 0, "lineBreakAssists": 0, "runsNormalMetres": 0, "runsNormal": 0, "runsKickReturnMetres": 0, "playerId": 991438, "jumperNumber": 13, "fieldGoals": 0, "penaltyGoals": 0, "runs": 0}, {"tries": 0, "runsDummyHalfMetres": 0, "sinBins": 0, "onReports": 0, "runsHitupMetres": 0, "tryAssists": 0, "penaltyGoalAttempts": 0, "points": 0, "conversionsUnsuccessful": 0, "possessions": 0, "tackleds": 0, "kickMetres": 0, "kicksGeneralPlay": 0, "tackles": 0, "tacklesIneffective": 0, "handlingErrors": 0, "sentOffs": 0, "runsDummyHalf": 0, "squadId": 336, "offloads": 0, "bombKicksCaught": 0, "runsKickReturn": 0, "runsHitup": 0, "fieldGoalAttempts": 0, "conversionAttempts": 0, "penaltiesConceded": 0, "postContactMetres": 0, "position": "Interchange", "errors": 0, "goalLineDropouts": 0, "fortyTwenty": 0, "conversions": 0, "tryDebits": 0, "missedTackles": 0, "penaltyGoalsUnsuccessful": 0, "kicksCaught": 0, "metresGained": 0, "lineBreaks": 0, "tackleBreaks": 0, "trySaves": 0, "passes": 0, "runMetres": 0, "fieldGoalsUnsuccessful": 0, "lineBreakAssists": 0, "runsNormalMetres": 0, "runsNormal": 0, "runsKickReturnMetres": 0, "playerId": 1019596, "jumperNumber": 14, "fieldGoals": 0, "penaltyGoals": 0, "runs": 0}, {"tries": 0, "runsDummyHalfMetres": 0, "sinBins": 0, "onReports": 0, "runsHitupMetres": 0, "tryAssists": 0, "penaltyGoalAttempts": 0, "points": 0, "conversionsUnsuccessful": 0, "possessions": 0, "tackleds": 0, "kickMetres": 0, "kicksGeneralPlay": 0, "tackles": 0, "tacklesIneffective": 0, "handlingErrors": 0, "sentOffs": 0, "runsDummyHalf": 0, "squadId": 336, "offloads": 0, "bombKicksCaught": 0, "runsKickReturn": 0, "runsHitup": 0, "fieldGoalAttempts": 0, "conversionAttempts": 0, "penaltiesConceded": 0, "postContactMetres": 0, "position": "Interchange", "errors": 0, "goalLineDropouts": 0, "fortyTwenty": 0, "conversions": 0, "tryDebits": 0, "missedTackles": 0, "penaltyGoalsUnsuccessful": 0, "kicksCaught": 0, "metresGained": 0, "lineBreaks": 0, "tackleBreaks": 0, "trySaves": 0, "passes": 0, "runMetres": 0, "fieldGoalsUnsuccessful": 0, "lineBreakAssists": 0, "runsNormalMetres": 0, "runsNormal": 0, "runsKickReturnMetres": 0, "playerId": 1001235, "jumperNumber": 15, "fieldGoals": 0, "penaltyGoals": 0, "runs": 0}, {"tries": 0, "runsDummyHalfMetres": 0, "sinBins": 0, "onReports": 0, "runsHitupMetres": 0, "tryAssists": 0, "penaltyGoalAttempts": 0, "points": 0, "conversionsUnsuccessful": 0, "possessions": 0, "tackleds": 0, "kickMetres": 0, "kicksGeneralPlay": 0, "tackles": 0, "tacklesIneffective": 0, "handlingErrors": 0, "sentOffs": 0, "runsDummyHalf": 0, "squadId": 336, "offloads": 0, "bombKicksCaught": 0, "runsKickReturn": 0, "runsHitup": 0, "fieldGoalAttempts": 0, "conversionAttempts": 0, "penaltiesConceded": 0, "postContactMetres": 0, "position": "Interchange", "errors": 0, "goalLineDropouts": 0, "fortyTwenty": 0, "conversions": 0, "tryDebits": 0, "missedTackles": 0, "penaltyGoalsUnsuccessful": 0, "kicksCaught": 0, "metresGained": 0, "lineBreaks": 0, "tackleBreaks": 0, "trySaves": 0, "passes": 0, "runMetres": 0, "fieldGoalsUnsuccessful": 0, "lineBreakAssists": 0, "runsNormalMetres": 0, "runsNormal": 0, "runsKickReturnMetres": 0, "playerId": 1019536, "jumperNumber": 16, "fieldGoals": 0, "penaltyGoals": 0, "runs": 0}, {"tries": 0, "runsDummyHalfMetres": 0, "sinBins": 0, "onReports": 0, "runsHitupMetres": 0, "tryAssists": 0, "penaltyGoalAttempts": 0, "points": 0, "conversionsUnsuccessful": 0, "possessions": 0, "tackleds": 0, "kickMetres": 0, "kicksGeneralPlay": 0, "tackles": 0, "tacklesIneffective": 0, "handlingErrors": 0, "sentOffs": 0, "runsDummyHalf": 0, "squadId": 336, "offloads": 0, "bombKicksCaught": 0, "runsKickReturn": 0, "runsHitup": 0, "fieldGoalAttempts": 0, "conversionAttempts": 0, "penaltiesConceded": 0, "postContactMetres": 0, "position": "Interchange", "errors": 0, "goalLineDropouts": 0, "fortyTwenty": 0, "conversions": 0, "tryDebits": 0, "missedTackles": 0, "penaltyGoalsUnsuccessful": 0, "kicksCaught": 0, "metresGained": 0, "lineBreaks": 0, "tackleBreaks": 0, "trySaves": 0, "passes": 0, "runMetres": 0, "fieldGoalsUnsuccessful": 0, "lineBreakAssists": 0, "runsNormalMetres": 0, "runsNormal": 0, "runsKickReturnMetres": 0, "playerId": 1043836, "jumperNumber": 17, "fieldGoals": 0, "penaltyGoals": 0, "runs": 0}, {"tries": 0, "runsDummyHalfMetres": 0, "sinBins": 0, "onReports": 0, "runsHitupMetres": 0, "tryAssists": 0, "penaltyGoalAttempts": 0, "points": 0, "conversionsUnsuccessful": 0, "possessions": 0, "tackleds": 0, "kickMetres": 0, "kicksGeneralPlay": 0, "tackles": 0, "tacklesIneffective": 0, "handlingErrors": 0, "sentOffs": 0, "runsDummyHalf": 0, "squadId": 336, "offloads": 0, "bombKicksCaught": 0, "runsKickReturn": 0, "runsHitup": 0, "fieldGoalAttempts": 0, "conversionAttempts": 0, "penaltiesConceded": 0, "postContactMetres": 0, "position": "Interchange", "errors": 0, "goalLineDropouts": 0, "fortyTwenty": 0, "conversions": 0, "tryDebits": 0, "missedTackles": 0, "penaltyGoalsUnsuccessful": 0, "kicksCaught": 0, "metresGained": 0, "lineBreaks": 0, "tackleBreaks": 0, "trySaves": 0, "passes": 0, "runMetres": 0, "fieldGoalsUnsuccessful": 0, "lineBreakAssists": 0, "runsNormalMetres": 0, "runsNormal": 0, "runsKickReturnMetres": 0, "playerId": 1034034, "jumperNumber": 18, "fieldGoals": 0, "penaltyGoals": 0, "runs": 0}, {"tries": 0, "runsDummyHalfMetres": 0, "sinBins": 0, "onReports": 0, "runsHitupMetres": 0, "tryAssists": 0, "penaltyGoalAttempts": 0, "points": 0, "conversionsUnsuccessful": 0, "possessions": 0, "tackleds": 0, "kickMetres": 0, "kicksGeneralPlay": 0, "tackles": 0, "tacklesIneffective": 0, "handlingErrors": 0, "sentOffs": 0, "runsDummyHalf": 0, "squadId": 336, "offloads": 0, "bombKicksCaught": 0, "runsKickReturn": 0, "runsHitup": 0, "fieldGoalAttempts": 0, "conversionAttempts": 0, "penaltiesConceded": 0, "postContactMetres": 0, "position": "Interchange", "errors": 0, "goalLineDropouts": 0, "fortyTwenty": 0, "conversions": 0, "tryDebits": 0, "missedTackles": 0, "penaltyGoalsUnsuccessful": 0, "kicksCaught": 0, "metresGained": 0, "lineBreaks": 0, "tackleBreaks": 0, "trySaves": 0, "passes": 0, "runMetres": 0, "fieldGoalsUnsuccessful": 0, "lineBreakAssists": 0, "runsNormalMetres": 0, "runsNormal": 0, "runsKickReturnMetres": 0, "playerId": 1039754, "jumperNumber": 19, "fieldGoals": 0, "penaltyGoals": 0, "runs": 0}, {"tries": 0, "runsDummyHalfMetres": 0, "sinBins": 0, "onReports": 0, "runsHitupMetres": 0, "tryAssists": 0, "penaltyGoalAttempts": 0, "points": 0, "conversionsUnsuccessful": 0, "possessions": 0, "tackleds": 0, "kickMetres": 0, "kicksGeneralPlay": 0, "tackles": 0, "tacklesIneffective": 0, "handlingErrors": 0, "sentOffs": 0, "runsDummyHalf": 0, "squadId": 336, "offloads": 0, "bombKicksCaught": 0, "runsKickReturn": 0, "runsHitup": 0, "fieldGoalAttempts": 0, "conversionAttempts": 0, "penaltiesConceded": 0, "postContactMetres": 0, "position": "Interchange", "errors": 0, "goalLineDropouts": 0, "fortyTwenty": 0, "conversions": 0, "tryDebits": 0, "missedTackles": 0, "penaltyGoalsUnsuccessful": 0, "kicksCaught": 0, "metresGained": 0, "lineBreaks": 0, "tackleBreaks": 0, "trySaves": 0, "passes": 0, "runMetres": 0, "fieldGoalsUnsuccessful": 0, "lineBreakAssists": 0, "runsNormalMetres": 0, "runsNormal": 0, "runsKickReturnMetres": 0, "playerId": 1048340, "jumperNumber": 20, "fieldGoals": 0, "penaltyGoals": 0, "runs": 0}, {"tries": 0, "runsDummyHalfMetres": 0, "sinBins": 0, "onReports": 0, "runsHitupMetres": 0, "tryAssists": 0, "penaltyGoalAttempts": 0, "points": 0, "conversionsUnsuccessful": 0, "possessions": 0, "tackleds": 0, "kickMetres": 0, "kicksGeneralPlay": 0, "tackles": 0, "tacklesIneffective": 0, "handlingErrors": 0, "sentOffs": 0, "runsDummyHalf": 0, "squadId": 336, "offloads": 0, "bombKicksCaught": 0, "runsKickReturn": 0, "runsHitup": 0, "fieldGoalAttempts": 0, "conversionAttempts": 0, "penaltiesConceded": 0, "postContactMetres": 0, "position": "Interchange", "errors": 0, "goalLineDropouts": 0, "fortyTwenty": 0, "conversions": 0, "tryDebits": 0, "missedTackles": 0, "penaltyGoalsUnsuccessful": 0, "kicksCaught": 0, "metresGained": 0, "lineBreaks": 0, "tackleBreaks": 0, "trySaves": 0, "passes": 0, "runMetres": 0, "fieldGoalsUnsuccessful": 0, "lineBreakAssists": 0, "runsNormalMetres": 0, "runsNormal": 0, "runsKickReturnMetres": 0, "playerId": 1033195, "jumperNumber": 21, "fieldGoals": 0, "penaltyGoals": 0, "runs": 0}, {"tries": 0, "runsDummyHalfMetres": 0, "sinBins": 0, "onReports": 0, "runsHitupMetres": 0, "tryAssists": 0, "penaltyGoalAttempts": 0, "points": 0, "conversionsUnsuccessful": 0, "possessions": 0, "tackleds": 0, "kickMetres": 0, "kicksGeneralPlay": 0, "tackles": 0, "tacklesIneffective": 0, "handlingErrors": 0, "sentOffs": 0, "runsDummyHalf": 0, "squadId": 336, "offloads": 0, "bombKicksCaught": 0, "runsKickReturn": 0, "runsHitup": 0, "fieldGoalAttempts": 0, "conversionAttempts": 0, "penaltiesConceded": 0, "postContactMetres": 0, "position": "Extended Bench 5", "errors": 0, "goalLineDropouts": 0, "fortyTwenty": 0, "conversions": 0, "tryDebits": 0, "missedTackles": 0, "penaltyGoalsUnsuccessful": 0, "kicksCaught": 0, "metresGained": 0, "lineBreaks": 0, "tackleBreaks": 0, "trySaves": 0, "passes": 0, "runMetres": 0, "fieldGoalsUnsuccessful": 0, "lineBreakAssists": 0, "runsNormalMetres": 0, "runsNormal": 0, "runsKickReturnMetres": 0, "playerId": 1035329, "jumperNumber": 22, "fieldGoals": 0, "penaltyGoals": 0, "runs": 0}]}, "playerPeriodStats": {"player": []}, "teamPeriodStats": {"team": []}, "playerSubs": {}, "scoreFlow": {"score": []}, "teamStats": {"team": [{"timeInOwnHalf": 0, "timeInOppHalf": 0, "tries": 0, "runsDummyHalfMetres": 0, "sinBins": 0, "onReports": 0, "runsHitupMetres": 0, "setRestartsRuck": 0, "setRestarts10m": 0, "tryAssists": 0, "ineffectiveTackles": 0, "penaltyGoalAttempts": 0, "conversionsUnsuccessful": 0, "score": 0, "possessions": 0, "tackleds": 0, "kickMetres": 0, "kicksGeneralPlay": 0, "completionRatePercentage": 0, "tackles": 0, "incompleteSets": 0, "tacklesIneffective": 0, "handlingErrors": 0, "completeSets": 0, "sentOffs": 0, "runsDummyHalf": 0, "squadId": 332, "offloads": 0, "bombKicksCaught": 0, "runsKickReturn": 0, "runsHitup": 0, "fieldGoalAttempts": 0, "conversionAttempts": 0, "penaltiesConceded": 0, "timeInOwn20": 0, "tacklesMissed": 0, "postContactMetres": 0, "setRestarts": 0, "errors": 0, "goalLineDropouts": 0, "fortyTwenty": 0, "conversions": 0, "missedTackles": 0, "kicksCaught": 0, "metresGained": 0, "lineBreaks": 0, "possessionPercentage": 0, "tackleBreaks": 0, "trySaves": 0, "passes": 0, "runMetres": 0, "lineBreakAssists": 0, "runsNormalMetres": 0, "scrumWins": 0, "runsNormal": 0, "runsKickReturnMetres": 0, "timeInOpp20": 0, "fieldGoals": 0, "penaltyGoals": 0, "runs": 0}, {"timeInOwnHalf": 0, "timeInOppHalf": 0, "tries": 0, "runsDummyHalfMetres": 0, "sinBins": 0, "onReports": 0, "runsHitupMetres": 0, "setRestartsRuck": 0, "setRestarts10m": 0, "tryAssists": 0, "ineffectiveTackles": 0, "penaltyGoalAttempts": 0, "conversionsUnsuccessful": 0, "score": 0, "possessions": 0, "tackleds": 0, "kickMetres": 0, "kicksGeneralPlay": 0, "completionRatePercentage": 0, "tackles": 0, "incompleteSets": 0, "tacklesIneffective": 0, "handlingErrors": 0, "completeSets": 0, "sentOffs": 0, "runsDummyHalf": 0, "squadId": 336, "offloads": 0, "bombKicksCaught": 0, "runsKickReturn": 0, "runsHitup": 0, "fieldGoalAttempts": 0, "conversionAttempts": 0, "penaltiesConceded": 0, "timeInOwn20": 0, "tacklesMissed": 0, "postContactMetres": 0, "setRestarts": 0, "errors": 0, "goalLineDropouts": 0, "fortyTwenty": 0, "conversions": 0, "missedTackles": 0, "kicksCaught": 0, "metresGained": 0, "lineBreaks": 0, "possessionPercentage": 0, "tackleBreaks": 0, "trySaves": 0, "passes": 0, "runMetres": 0, "lineBreakAssists": 0, "runsNormalMetres": 0, "scrumWins": 0, "runsNormal": 0, "runsKickReturnMetres": 0, "timeInOpp20": 0, "fieldGoals": 0, "penaltyGoals": 0, "runs": 0}]}}}